ngv_ctools-1.0.4.dist-info/RECORD
ngv_ctools-1.0.4.dist-info/METADATA
ngv_ctools-1.0.4.dist-info/WHEEL
ngv_ctools-1.0.4.dist-info/licenses/LICENSE.txt
ngv_ctools-1.0.4.dist-info/licenses/AUTHORS.txt
ngv_ctools/_ngv_ctools.cpython-310-x86_64-linux-gnu.so
ngv_ctools/__init__.py
ngv_ctools/fast_marching_method/__init__.py
