Metadata-Version: 2.1
Name: ngv-ctools
Version: 1.0.4
Summary: NGV Architecture c++ modules
Author: Blue Brain Project, EPFL
License:                                  Apache License
Classifier: Programming Language :: Python
Classifier: Programming Language :: Python :: 3.9
Classifier: Programming Language :: Python :: 3.10
Classifier: Programming Language :: Python :: 3.11
Classifier: Programming Language :: Python :: 3.12
Classifier: Programming Language :: Python :: 3.13
Project-URL: Homepage, https://github.com/BlueBrain/ngv-ctools
Project-URL: Repository, https://github.com/BlueBrain/ngv-ctools
Project-URL: Issues, https://github.com/BlueBrain/ngv-ctools/issues
Project-URL: Tracker, https://github.com/BlueBrain/ngv-ctools/issues
Requires-Python: >=3.8
